src/__init__.py
src/main.py
src/modules/logging/__init__.py
src/modules/logging/base.py
src/modules/logging/colorful.py
src/modules/logging/json.py
src/modules/logging/plain.py
src/modules/playbook/checkpoint/__init__.py
src/modules/playbook/checkpoint/base.py
src/modules/playbook/checkpoint/factory.py
src/modules/playbook/checkpoint/file.py
src/modules/playbook/command/run.py
src/modules/playbook/commands.py
src/modules/playbook/config.py
src/modules/playbook/context/execution_context.py
src/modules/playbook/managers/checkpoint_manager.py
src/modules/playbook/managers/config_renderer.py
src/modules/playbook/managers/execution_tracker.py
src/modules/playbook/managers/observer_manager.py
src/modules/playbook/managers/session_manager.py
src/modules/playbook/metrics/__init__.py
src/modules/playbook/metrics/base.py
src/modules/playbook/metrics/console.py
src/modules/playbook/metrics/factory.py
src/modules/playbook/metrics/json.py
src/modules/playbook/metrics/prometheus.py
src/modules/playbook/observer/__init__.py
src/modules/playbook/observer/base.py
src/modules/playbook/observer/events.py
src/modules/playbook/observer/metrics_observer.py
src/modules/playbook/playbook.py
src/modules/playbook/template_renderer.py
src/modules/playbook/validator.py
src/modules/playbook/variables.py
src/modules/request/aio_client_cache.py
src/modules/request/circuit_breaker.py
src/modules/request/client_factory.py
src/modules/request/command/__init__.py
src/modules/request/command/request.py
src/modules/request/commands.py
src/modules/request/errors.py
src/modules/request/resilient_http_client.py
src/modules/session/auth/__init__.py
src/modules/session/auth/api_key.py
src/modules/session/auth/base.py
src/modules/session/auth/basic.py
src/modules/session/auth/bearer.py
src/modules/session/auth/factory.py
src/modules/session/auth/oauth2.py
src/modules/session/command/create_session.py
src/modules/session/commands.py
src/modules/session/session.py
src/modules/session/session_store.py
restbook-0.3.9.dist-info/METADATA
restbook-0.3.9.dist-info/WHEEL
restbook-0.3.9.dist-info/entry_points.txt
restbook-0.3.9.dist-info/RECORD
