Metadata-Version: 2.3
Name: restbook
Version: 0.3.9
Summary: simple rest api for testing
Author: Shalev Avhar
Author-email: shalev1994avhar@gmail.com
Requires-Python: >=3.12,<4.0
Classifier: Programming Language :: Python :: 3
Classifier: Programming Language :: Python :: 3.12
Classifier: Programming Language :: Python :: 3.13
Requires-Dist: aiohttp (>=3.9.3,<4.0.0)
Requires-Dist: click (>=8.1.8,<9.0.0)
Requires-Dist: croniter (>=6.0.0,<7.0.0)
Requires-Dist: jinja2 (>=3.1.6,<4.0.0)
Requires-Dist: jq (>=1.8.0,<2.0.0)
Requires-Dist: loguru (>=0.7.3,<0.8.0)
Requires-Dist: prometheus-client (>=0.21.1,<0.22.0)
Requires-Dist: prompt-toolkit (>=3.0.50,<4.0.0)
Requires-Dist: pydantic (>=2.10.6,<3.0.0)
Requires-Dist: pyyaml (>=6.0.2,<7.0.0)
Requires-Dist: requests (>=2.31.0,<3.0.0)
